biomaj_cli/__init__.py
biomaj_cli/utils.py
biomaj_cli-3.1.11.data/scripts/biomaj-cli.py
biomaj_cli-3.1.11.dist-info/LICENSE
biomaj_cli-3.1.11.dist-info/METADATA
biomaj_cli-3.1.11.dist-info/WHEEL
biomaj_cli-3.1.11.dist-info/top_level.txt
biomaj_cli-3.1.11.dist-info/RECORD
